django_modern_rest/__init__.py
django_modern_rest/example.py
django_modern_rest/py.typed
django_modern_rest-0.0.0.dist-info/METADATA
django_modern_rest-0.0.0.dist-info/WHEEL
django_modern_rest-0.0.0.dist-info/licenses/LICENSE
django_modern_rest-0.0.0.dist-info/RECORD
